async_multiplexer/__init__.py
async_multiplexer/multiplex_listener.py
async_multiplexer/multiplexer.py
async_multiplexer/protocol.py
tests/__init__.py
tests/conftest.py
tests/test_multiplexer.py
tests/test_multiplexer_listener.py
tests/test_protocol.py
tests/utils.py
async_multiplexer-0.1.0.dist-info/LICENSE
async_multiplexer-0.1.0.dist-info/METADATA
async_multiplexer-0.1.0.dist-info/WHEEL
async_multiplexer-0.1.0.dist-info/top_level.txt
async_multiplexer-0.1.0.dist-info/RECORD
