Metadata-Version: 2.1
Name: async-multiplexer
Version: 0.1.0
Summary: Asyncio TCP Multiplexer
Home-page: https://github.com/aratz-lasa/async-multiplexer
Author: Aratz M. Lasa
Author-email: aratz.m.lasa@gmail.com
License: UNKNOWN
Platform: UNKNOWN
Classifier: Programming Language :: Python :: 3
Classifier: License :: OSI Approved :: MIT License
Classifier: Operating System :: OS Independent
Requires-Python: >=3.8
Requires-Dist: uvarint (==1.2.0)
Provides-Extra: dev
Requires-Dist: pytest (==5.4.1) ; extra == 'dev'
Requires-Dist: pytest-asyncio (==0.11.0) ; extra == 'dev'
Requires-Dist: hypothesis (==5.10.4) ; extra == 'dev'
Requires-Dist: hypothesis-pytest (==0.19.0) ; extra == 'dev'
